{
  "weight": 10,
  "density": 1,
  "min_height": 30,
  "max_height": 60,
  "dimension_filter": ["dimension_id:10"],

  "surface_stone_material": "iron",
  "name": "Enriched Iron Vein",
  "description": "Incredibly rare! 1 in 180 chance to spawn. Only contains pure iron!",

  "generator": {
    "type": "ellipsoid",
    "radius": [20, 20]

  },
  "filler": {
    "type": "ga_simple",
    "value": {
      "type": "weight_random",
      "values": [
		{
          "weight": 50,
          "value": "ore:pure:iron"
        },
		{
          "weight": 45,
          "value": "ore:pure:magnetite"
        },	
		{
          "weight": 5,
          "value": "ore:poor:gold"
        }
	]
    }
  }
}